fGOaria/__init__.py
fGOaria/classes/__init__.py
fGOaria/classes/api_client.py
fGOaria/classes/aria_client.py
fGOaria/classes/bucket.py
fGOaria/classes/cli_data_manager.py
fGOaria/classes/cli_techeval.py
fGOaria/classes/client_data_manager.py
fGOaria/classes/client_oauth.py
fGOaria/classes/client_review.py
fGOaria/classes/data_manager.py
fGOaria/classes/field.py
fGOaria/classes/oauth.py
fGOaria/classes/queries.py
fGOaria/classes/record.py
fGOaria/classes/technical_review.py
fGOaria/classes/token.py
fGOaria/classes/visit.py
fGOaria/commands/__init__.py
fGOaria/commands/cli.py
fGOaria/commands/create_bucket.py
fGOaria/commands/create_field.py
fGOaria/commands/create_record.py
fGOaria/commands/list_buckets.py
fGOaria/commands/list_fields.py
fGOaria/commands/list_records.py
fGOaria/commands/login.py
fGOaria/commands/tech_eval.py
fGOaria/utils/__init__.py
fGOaria/utils/constants.py
fGOaria/utils/encryption.py
fGOaria/utils/imports_config.py
fGOaria/utils/utility_functions.py
fandango_aria-2.2.4.dist-info/licenses/LICENSE.txt
fandango_aria-2.2.4.dist-info/METADATA
fandango_aria-2.2.4.dist-info/WHEEL
fandango_aria-2.2.4.dist-info/entry_points.txt
fandango_aria-2.2.4.dist-info/top_level.txt
fandango_aria-2.2.4.dist-info/RECORD
