Metadata-Version: 2.4
Name: fandanGO-aria
Version: 2.2.4
Summary: ARIA connection for managing access and metadata deposition, primarily through fandanGO
Home-page: https://github.com/FragmentScreen/fandanGO-aria
Author: Lui Holliday, Instruct-ERIC
Author-email: lui.holliday@instruct-eric.org
License: MIT
License-File: LICENSE.txt
Requires-Dist: click
Requires-Dist: requests
Requires-Dist: keyring
Requires-Dist: python-dotenv
Requires-Dist: questionary
Requires-Dist: PyYAML
Requires-Dist: cryptography
Dynamic: author
Dynamic: author-email
Dynamic: description
Dynamic: description-content-type
Dynamic: home-page
Dynamic: license
Dynamic: license-file
Dynamic: requires-dist
Dynamic: summary
